{
  "companion_test_path": null,
  "description": "Convert REAL Solana / Anchor / SVM ecosystem security findings into",
  "honest_zero": false,
  "last_run_commit_sha": "bd5aa18d4a5b4ba7a636b948a9fbc041619e1a53",
  "makefile_target": null,
  "miner_slug": "solana_svm",
  "record_count_emitted": 27,
  "schema": "auditooor.hackerman_etl_miner_registry_entry.v1",
  "source_channel": "corpus-bridge",
  "target_subtree": "audit/corpus_tags/tags/solana_svm",
  "target_subtree_exists_on_disk": true,
  "tool_path": "tools/hackerman-etl-from-solana-svm.py",
  "verification_tier": "tier-2"
}
